{
    "project_name": "Tesla_Battery_Line_C_Advanced",
    "process_description": "A high-speed battery assembly line. The process starts with mixing, then moves to coating and drying. Note that the drying oven is very long. After drying, the line splits into two parallel winding units before converging back for assembly and filling. The layout should be compact.",
    "machines": [
        {
            "id": "m_mix",
            "name": "Anode Mixer",
            "length": 3000,
            "width": 2500
        },
        {
            "id": "m_coat",
            "name": "Coating Machine",
            "length": 4000,
            "width": 2000
        },
        {
            "id": "m_dry",
            "name": "Drying Oven",
            "length": 8000,
            "width": 3000
        },
        {
            "id": "m_cal",
            "name": "Calendaring Press",
            "length": 2500,
            "width": 2500
        },
        {
            "id": "m_slit",
            "name": "Slitting Machine",
            "length": 2000,
            "width": 1500
        },
        {
            "id": "m_wind_1",
            "name": "Winding Unit 1",
            "length": 1500,
            "width": 1500
        },
        {
            "id": "m_wind_2",
            "name": "Winding Unit 2",
            "length": 1500,
            "width": 1500
        },
        {
            "id": "m_asm",
            "name": "Assembly Robot",
            "length": 2000,
            "width": 2000
        },
        {
            "id": "m_fill",
            "name": "Electrolyte Filler",
            "length": 3000,
            "width": 2000
        }
    ],
    "relationships": [
        {
            "from_id": "m_mix",
            "to_id": "m_coat",
            "type": "pump_line"
        },
        {
            "from_id": "m_coat",
            "to_id": "m_dry",
            "type": "conveyor"
        },
        {
            "from_id": "m_dry",
            "to_id": "m_cal",
            "type": "roller_conveyor"
        },
        {
            "from_id": "m_cal",
            "to_id": "m_slit",
            "type": "conveyor"
        },
        {
            "from_id": "m_slit",
            "to_id": "m_wind_1",
            "type": "diverter"
        },
        {
            "from_id": "m_slit",
            "to_id": "m_wind_2",
            "type": "diverter"
        },
        {
            "from_id": "m_wind_1",
            "to_id": "m_asm",
            "type": "agv_path"
        },
        {
            "from_id": "m_wind_2",
            "to_id": "m_asm",
            "type": "agv_path"
        },
        {
            "from_id": "m_asm",
            "to_id": "m_fill",
            "type": "conveyor"
        }
    ]
}